cloudcoil/models/prometheus_operator/__init__.py
cloudcoil/models/prometheus_operator/py.typed
cloudcoil/models/prometheus_operator/v1.py
cloudcoil/models/prometheus_operator/v1alpha1.py
cloudcoil_models_prometheus_operator-0.80.1.0.dist-info/METADATA
cloudcoil_models_prometheus_operator-0.80.1.0.dist-info/WHEEL
cloudcoil_models_prometheus_operator-0.80.1.0.dist-info/licenses/LICENSE
cloudcoil_models_prometheus_operator-0.80.1.0.dist-info/RECORD
